MANIFEST.in
README.md
setup.py
front_end/__init__.py
front_end/app.py
front_end/main_app.py
molecular_interaction_rules/__init__.py
molecular_interaction_rules/molecular_database.py
molecular_interaction_rules.egg-info/PKG-INFO
molecular_interaction_rules.egg-info/SOURCES.txt
molecular_interaction_rules.egg-info/dependency_links.txt
molecular_interaction_rules.egg-info/not-zip-safe
molecular_interaction_rules.egg-info/top_level.txt
molecular_interaction_rules/ions/__init__.py
molecular_interaction_rules/ions/potassium.py
molecular_interaction_rules/ions/sodium.py
molecular_interaction_rules/molecules/__init__.py
molecular_interaction_rules/molecules/aromatic/__init__.py
molecular_interaction_rules/molecules/aromatic/azulene.py
molecular_interaction_rules/molecules/aromatic/benzene.py
molecular_interaction_rules/molecules/aromatic/bipyrrole.py
molecular_interaction_rules/molecules/aromatic/bromobenzene.py
molecular_interaction_rules/molecules/aromatic/chlorobenzene.py
molecular_interaction_rules/molecules/aromatic/fluorobenzene.py
molecular_interaction_rules/molecules/aromatic/four_pyridinone.py
molecular_interaction_rules/molecules/aromatic/furan.py
molecular_interaction_rules/molecules/aromatic/imidazole.py
molecular_interaction_rules/molecules/aromatic/imidazolium.py
molecular_interaction_rules/molecules/aromatic/indole.py
molecular_interaction_rules/molecules/aromatic/indolizine.py
molecular_interaction_rules/molecules/aromatic/iodobenzene.py
molecular_interaction_rules/molecules/aromatic/isoxazole.py
molecular_interaction_rules/molecules/aromatic/methyleneoxindole.py
molecular_interaction_rules/molecules/aromatic/nitrobenzene.py
molecular_interaction_rules/molecules/aromatic/one_phenyl_four_pyridinone.py
molecular_interaction_rules/molecules/aromatic/phenol.py
molecular_interaction_rules/molecules/aromatic/phenoxazine.py
molecular_interaction_rules/molecules/aromatic/pyridine.py
molecular_interaction_rules/molecules/aromatic/pyridinium.py
molecular_interaction_rules/molecules/aromatic/pyrimidine.py
molecular_interaction_rules/molecules/aromatic/pyrrolidine.py
molecular_interaction_rules/molecules/aromatic/thiophene.py
molecular_interaction_rules/molecules/aromatic/three_amino_pyridine.py
